fitrate/__init__.py
fitrate/_fit.py
fitrate/utils.py
fitrate-1.0.0.dist-info/LICENSE
fitrate-1.0.0.dist-info/WHEEL
fitrate-1.0.0.dist-info/METADATA
fitrate-1.0.0.dist-info/RECORD
