Metadata-Version: 2.1
Name: fitrate
Version: 1.0.0
Summary: Calculate the length of the sides that fit into the limited volume
Home-page: https://github.com/suzukey/fitrate
Author: suzukey
Author-email: suzukei0208@gmail.com
Requires-Python: >=3.6,<4.0
Classifier: Programming Language :: Python :: 3
Classifier: Programming Language :: Python :: 3.6
Classifier: Programming Language :: Python :: 3.7
Classifier: Programming Language :: Python :: 3.8
Project-URL: Repository, https://github.com/suzukey/fitrate
